kwrappers_s3ops-0.2.79-py2.7-nspkg.pth
kwrappers/s3ops/__init__.py
kwrappers/s3ops/general.py
kwrappers/s3ops/s3.py
kwrappers/s3ops/s3tasks.py
kwrappers_s3ops-0.2.79.data/data/requirements.txt
kwrappers_s3ops-0.2.79.data/data/version.txt
kwrappers_s3ops-0.2.79.dist-info/METADATA
kwrappers_s3ops-0.2.79.dist-info/RECORD
kwrappers_s3ops-0.2.79.dist-info/WHEEL
kwrappers_s3ops-0.2.79.dist-info/namespace_packages.txt
kwrappers_s3ops-0.2.79.dist-info/top_level.txt
