Metadata-Version: 2.1
Name: kwrappers-s3ops
Version: 0.2.79
Summary: S3 operations.
Home-page: https://bitbucket.org/tim_kablamo/kwrappers
Author: Tim Elson
Author-email: tim.elson@kablamo.com.au
License: MIT
Platform: UNKNOWN
